soufi_stream/__init__.py
soufi_stream/audio_recorder.py
soufi_stream/templates/audio_recorder.html
soufi_stream-0.1.1.dist-info/licenses/LICENSE
soufi_stream-0.1.1.dist-info/METADATA
soufi_stream-0.1.1.dist-info/WHEEL
soufi_stream-0.1.1.dist-info/top_level.txt
soufi_stream-0.1.1.dist-info/RECORD
