Metadata-Version: 2.4
Name: soufi-stream
Version: 0.1.1
Summary: A customizable audio recorder component for Streamlit
Home-page: https://github.com/soufiiyane/streamlit-realtime-recorder
Author: Soufiyane AIT MOULAY
Author-email: Soufiyane AIT MOULAY <soufiyane.aitmoulay@gmail.com>
Project-URL: Bug Tracker, https://github.com/soufiiyane/streamlit-realtime-recorder/issues
Classifier: Programming Language :: Python :: 3
Classifier: License :: OSI Approved :: MIT License
Classifier: Operating System :: OS Independent
Requires-Python: >=3.11
License-File: LICENSE
Requires-Dist: streamlit>=1.0.0
Dynamic: author
Dynamic: home-page
Dynamic: license-file
Dynamic: requires-python
